README.rst
setup.cfg
setup.py
pyarlo/__init__.py
pyarlo/base_station.py
pyarlo/camera.py
pyarlo/const.py
pyarlo/media.py
pyarlo/utils.py
pyarlo.egg-info/PKG-INFO
pyarlo.egg-info/SOURCES.txt
pyarlo.egg-info/dependency_links.txt
pyarlo.egg-info/requires.txt
pyarlo.egg-info/top_level.txt