Metadata-Version: 1.1
Name: pyarlo
Version: 0.2.2
Summary: Python Arlo is a library written in Python 2.7/3x that exposes the Netgear Arlo cameras as Python objects.
Home-page: https://github.com/tchellomello/python-arlo
Author: Marcelo Moreira de Mello
Author-email: tchello.mello@gmail.com
License: LGPLv3+
Keywords: arlo,netgear,camera,home automation,python
Platform: UNKNOWN
Classifier: Environment :: Other Environment
Classifier: Intended Audience :: Developers
Classifier: License :: OSI Approved :: GNU Lesser General Public License v3 or later (LGPLv3+)
Classifier: Operating System :: OS Independent
Classifier: Programming Language :: Python
Classifier: Programming Language :: Python :: 2.7
Classifier: Programming Language :: Python :: 3.4
Classifier: Programming Language :: Python :: 3.5
Classifier: Programming Language :: Python :: 3.6
Classifier: Topic :: Software Development :: Libraries :: Python Modules
